Connector/AutoSendBuffer.py
Connector/Client.py
Connector/CloseablePipe.py
Connector/CloseableQueue.py
Connector/Config.py
Connector/Future.py
Connector/KillableThread.py
Connector/Node.py
Connector/NodeBasicMethods.py
Connector/NodeFileTransferMethods.py
Connector/NodeGlobalDictMethods.py
Connector/NodeGlobalQueuesMethods.py
Connector/NodeInternalClasses.py
Connector/NodeLocalDictMethods.py
Connector/NodeLocalPipesMethods.py
Connector/NodeLocalQueuesMethods.py
Connector/NodeRPCMethods.py
Connector/OrderedDict.py
Connector/Peer.py
Connector/Pipes.py
Connector/Queues.py
Connector/Server.py
Connector/ServerPeer.py
Connector/__init__.py
Connector/utils.py
tcp_connector-0.0.8.dist-info/LICENSE
tcp_connector-0.0.8.dist-info/METADATA
tcp_connector-0.0.8.dist-info/WHEEL
tcp_connector-0.0.8.dist-info/top_level.txt
tcp_connector-0.0.8.dist-info/RECORD
