Metadata-Version: 2.1
Name: tcp-connector
Version: 0.0.8
Summary: A lightweight network programming tool for Python
Home-page: https://github.com/Time-Coder/Glass-Engine
Author: Time-Coder
Author-email: binghui.wang@foxmail.com
Classifier: Programming Language :: Python :: 3
Classifier: License :: OSI Approved :: MIT License
Classifier: Operating System :: OS Independent
License-File: LICENSE
Requires-Dist: dill
Requires-Dist: netifaces
